columnflexpart/__init__.py
columnflexpart/classes/__init__.py
columnflexpart/classes/columnsetup.py
columnflexpart/classes/flexdataset.py
columnflexpart/classes/inversion.py
columnflexpart/classes/measurement.py
columnflexpart/scripts/__init__.py
columnflexpart/scripts/calc_results.py
columnflexpart/scripts/flexpart_safe_start.py
columnflexpart/scripts/prepare_config_partnum.py
columnflexpart/scripts/prepare_release.py
columnflexpart/scripts/read_sounding_positions.py
columnflexpart/scripts/split_releases.py
columnflexpart/scripts/static_position_times.py
columnflexpart/scripts/unpack_trajectories.py
columnflexpart/utils/__init__.py
columnflexpart/utils/plotting.py
columnflexpart/utils/utils.py
columnflexpart-0.1.dist-info/LICENCE
columnflexpart-0.1.dist-info/METADATA
columnflexpart-0.1.dist-info/WHEEL
columnflexpart-0.1.dist-info/top_level.txt
columnflexpart-0.1.dist-info/RECORD
